{
  "id": "problems_4",
  "title": "Бодлогууд",
  "body": [
    {
      "type": "header",
      "id": "problems_4",
      "value": "Бодлогууд"
    },
    {
      "type": "problem",
      "number": "4.1",
      "title": "Харилцан үйлчлэлийн энерги.",
      "statement": [
        {
          "type": "text",
          "value": "$q$ цэг цэнэг хязгааргүй дамжуулагч хавтгайгаас $l$ зайд байна. Хавтгай дэр суурилуулсан цэнэгтэй $q$ цэнэгийн харилцан үйлчлэлийн $W$ энергийг ол."
        }
      ],
      "solution": [
        {
          "type": "text",
          "value": "Хавтгай дэр тархсан цэнэгийг «хөлдөөж», $q$ цэнэгийг хязгааргүй зайд аваачихад $q$ цэнэг нь потенциалт оронд хөдлөх бөгөөд тэр орон нь хавтгайгаас нөгөө талд $l$ тогтмол зайд байх $-q$ дүрс цэнэгийн оронтой тэнцүү (тусгалын арга). Иймд:<br>$$W = -\\frac{1}{4\\pi\\varepsilon_0}\\frac{q^2}{2l}.$$"
        }
      ]
    },
    {
      "type": "problem",
      "number": "4.2",
      "title": "Өөрийн, харилцан ба бүрэн энерги.",
      "statement": [
        {
          "type": "text",
          "value": "Систем нь тус тус $q_1$ ба $q_2$ цэнэгтэй $R_1$ ба $R_2$ радиус бүхий хоёр концентрик металлан бүрхүүлээс тогтоно ($R_2 > R_1$). Нэг бүрийн өөрийн энерги $W_1$, $W_2$, бүрхүүлүүдийн харилцан үйлчлэлийн энерги $W_{\\text{хар}}$ болон системийн бүрэн цахилгаан энерги $W$-г ол."
        }
      ],
      "solution": [
        {
          "type": "text",
          "value": "(4.6)-ийн дагуу нэг бүр нь өөрийн цэнэгийн потенциалаар тодорхойлогдох өөрийн энергитэй:<br>$$W_{1,2} = \\frac{1}{4\\pi\\varepsilon_0}\\frac{q_{1,2}^2}{2R_{1,2}}.$$<br>Харилцан үйлчлэлийн энерги ($R_2 > R_1$):<br>$$W_{\\text{хар}} = \\frac{1}{4\\pi\\varepsilon_0}\\frac{q_1 q_2}{R_2}.$$<br>Бүрэн цахилгаан энерги:<br>$$W = \\frac{1}{4\\pi\\varepsilon_0}\\left(\\frac{q_1^2}{2R_1} + \\frac{q_2^2}{2R_2} + \\frac{q_1 q_2}{R_2}\\right).$$"
        }
      ]
    },
    {
      "type": "problem",
      "number": "4.3",
      "title": "",
      "statement": [
        {
          "type": "text",
          "value": "$R_1$ ба $R_2$ радиус бүхий хоёр жижиг металлан бөмбөлөг вакуум дотор тэдгээрийн хэмжээсээс хамаагүй их зайд байж тодорхой нийт цэнэгтэй байна. $q_1/q_2$ харьцаа ямар байхад системийн цахилгаан энерги хамгийн бага байх вэ? Энэ үед бөмбөлөгүүдийн хоорондох потенциалын зөрүү хэд вэ?"
        }
      ],
      "solution": [
        {
          "type": "text",
          "value": "Нийт $q$ цэнэгийг тогтмол байлгаад $\\partial W/\\partial q_1 = 0$ нөхцлөөс ($R_1, R_2 \\ll l$):<br>$$q_1 \\approx q\\frac{R_1}{R_1+R_2},\\quad q_2 \\approx q\\frac{R_2}{R_1+R_2},\\quad \\frac{q_1}{q_2} = \\frac{R_1}{R_2}.$$<br>$\\varphi \\sim q/R$ болохоор $\\varphi_1 = \\varphi_2$ — потенциалын зөрүү тэг байна."
        }
      ]
    },
    {
      "type": "problem",
      "number": "4.4",
      "title": "Орон дэрх энергийн локалчлал.",
      "statement": [
        {
          "type": "text",
          "value": "$q$ цэнэг $R$ радиус бүхий бөмбөрцөгт жигд тархсан байна. Диэлектрик тогтмол нь бүгдэд нэгтэй гэж үзэн бөмбөрцгийн өөрийн цахилгаан энерги болон бөмбөрцгийн дотор $W_1$ ба гаднах $W_2$ энергийн харьцааг ол."
        }
      ],
      "solution": [
        {
          "type": "text",
          "value": "Гаусын теоремоор орны хүчлэг:<br>$$E_1 = \\frac{q}{4\\pi\\varepsilon_0 R^3}\\,r\\;(r \\leq R),\\quad E_2 = \\frac{q}{4\\pi\\varepsilon_0 r^2}\\;(r \\geq R).$$<br>Бөмбөрцгийн өөрийн цахилгаан энерги:<br>$$W = \\frac{q^2}{8\\pi\\varepsilon_0 R}\\left(\\frac{1}{5}+1\\right) = \\frac{1}{4\\pi\\varepsilon_0}\\frac{3q^2}{5R},\\quad \\frac{W_1}{W_2} = \\frac{1}{5}.$$<br>$W_1/W_2$ харьцаа нь бөмбөрцгийн радиусаас үл хамаарна."
        }
      ]
    },
    {
      "type": "problem",
      "number": "4.5",
      "title": "",
      "statement": [
        {
          "type": "text",
          "value": "$q$ цэнэг нь $q_0$ цэг цэнэгийг агуулсан сферик бүрхүүлийн ($q$ цэнэг бүхий) төвд байна. Бүрхүүлийн радиус $R_1$-ээс $R_2$ болж томрох үеийн цахилгааны хүчний хийсэн ажлыг ол."
        }
      ],
      "solution": [
        {
          "type": "text",
          "value": "Хийсэн ажил нь цахилгаан энергийн буурлтай тэнцүү: $A = W_1 - W_2$. Бүрхүүл тэлэхэд орон зөвхөн $R_1$–$R_2$ хавтаст хэсэгт өөрчлөгдөнө (Зураг 4.5). Гаусын теоремоор:<br>$$E_1 = \\frac{q+q_0}{4\\pi\\varepsilon_0 r^2},\\quad E_2 = \\frac{q_0}{4\\pi\\varepsilon_0 r^2}.$$<br>Интеграллаад:<br>$$A = \\frac{q(q_0 + q/2)}{4\\pi\\varepsilon_0}\\left(\\frac{1}{R_1} - \\frac{1}{R_2}\\right).$$"
        },
        {
          "type": "image",
          "src": "images/irodov-electromagnetism/3e870b25-6320-483d-9133-cdd5212c2707-115_315_309_1212_125.jpg",
          "caption": "Зураг 4.5"
        }
      ]
    },
    {
      "type": "problem",
      "number": "4.6",
      "title": "",
      "statement": [
        {
          "type": "text",
          "value": "$q$ цэг цэнэг дотоод ба гадаад радиус нь тус тус $a$ ба $b$ болох цэнэггүй сфер дамжуулагчийн хавтасны төвд байна. $q$ цэнэгийг анхны байрлалаас жижиг нүхээр (Зураг 4.6) сфер хавтасны хавьтал зайд шилжүүлэхэд системийн цахилгааны хүчний хийсэн ажлыг ол."
        },
        {
          "type": "image",
          "src": "images/irodov-electromagnetism/3e870b25-6320-483d-9133-cdd5212c2707-116_310_392_588_762.jpg",
          "caption": "Зураг 4.6"
        }
      ],
      "solution": [
        {
          "type": "text",
          "value": "Орон зөвхөн $a$–$b$ хавтаст сфер хэсэгт өөрчлөгдөнө: эхний байрлалд тэнд орон байгаагүй, эцсийн байрлалд байна. Иймд:<br>$$A = -W_{\\text{хавт}} = -\\int_a^b \\frac{\\varepsilon_0 E^2}{2}\\,\\mathrm{d}V = \\frac{q^2}{8\\pi\\varepsilon_0}\\frac{a-b}{ab} < 0.$$"
        }
      ]
    },
    {
      "type": "problem",
      "number": "4.7",
      "title": "Конденсаторын хавтан ангасах ажил.",
      "statement": [
        {
          "type": "text",
          "value": "Хавтгай агаарт конденсатор байна, хавтан бүрийн талбай $S$. Хавтануудын хоорондох зайг $x_1$-ээс $x_2$ болгохын тулд цахилгааны хүчний эсрэг хийх $A^{\\prime}$ ажлыг олоорой, хэрэв 1) конденсаторын цэнэг $q$ тогтмол байвал; 2) конденсаторын хүчдэл $U$ тогтмол байвал. Хоёр тохиолдолд цахилгаан энергийн нэмэгдэл хэд вэ?"
        }
      ],
      "solution": [
        {
          "type": "text",
          "value": "1. Нэг хавтангийн ($E_1 = \\sigma/2\\varepsilon_0$) орон дэрх нөгоо хавтангийн цэнэг шилжих тул:<br>$$A^{\\prime} = \\frac{q^2}{2\\varepsilon_0 S}(x_2-x_1).$$<br>Энэ ажил энергийн нэмэгдэлд бүтнээр зарцуулагдана: $\\Delta W = A^{\\prime}$.<br>2. Элементар ажил:<br>$$\\delta A^{\\prime} = \\frac{\\varepsilon_0 S U^2}{2}\\frac{\\mathrm{d}x}{x^2}$$<br>Интеграллаад:<br>$$A^{\\prime} = \\frac{\\varepsilon_0 S U^2}{2}\\left(\\frac{1}{x_1} - \\frac{1}{x_2}\\right) > 0,\\quad \\Delta W = \\frac{\\varepsilon_0 S U^2}{2}\\left(\\frac{1}{x_2}-\\frac{1}{x_1}\\right) < 0.$$<br>$\\Delta W = -A^{\\prime}$ болж байна."
        }
      ]
    },
    {
      "type": "problem",
      "number": "4.8",
      "title": "Диэлектрик дэрх дамжуулагчдын хоорондах хүчүүд.",
      "statement": [
        {
          "type": "text",
          "value": "Хавтгай конденсаторыг $\\varepsilon$ диэлектрик тогтмолтой шингэн диэлектрикт хэвтээ байрлалаар дүрж, зазор нь диэлектрикоор дүүрсэн байна. Зазорын өргөн $h$. Конденсаторыг $U$ тогтмол хүчдэлд холбосон. Диэлектрикийн талаас хавтанд үйлчлэх нэгж гадаргуун хүч $f^{\\prime}$-г ол."
        }
      ],
      "solution": [
        {
          "type": "text",
          "value": "$f = f_0 - f^{\\prime}$ ба $f = f_0/\\varepsilon$, $f_0 = \\sigma^2/2\\varepsilon_0$, $\\sigma = \\varepsilon\\varepsilon_0 U/h$ болохоор:<br>$$f^{\\prime} = f_0\\left(1-\\frac{1}{\\varepsilon}\\right) = \\frac{\\varepsilon(\\varepsilon-1)\\varepsilon_0 U^2}{2h^2}.$$<br>Жишээ нь $U = 500$ В, $h = 1.0$ мм, $\\varepsilon = 81$ (ус) үед $f^{\\prime} = 7$ кПа."
        }
      ]
    },
    {
      "type": "problem",
      "number": "4.9",
      "title": "Диэлектрикт үйлчлэх хүч.",
      "statement": [
        {
          "type": "text",
          "value": "Цилиндрик конденсаторт $\\varepsilon$ диэлектрик тогтмолтой цилиндрик жигд диэлектрикийн давхарга оруулдаг. Дундаж радиус $R$, зай $d$ ($d \\ll R$). Конденсаторыг $U$ тогтмол хүчдэлд холбосон. Диэлектрикийг дотогш татах хүчийг ол."
        }
      ],
      "solution": [
        {
          "type": "text",
          "value": "(4.16) ба $d \\ll R$ нөхцлөөр:<br>$$C = \\frac{\\varepsilon_0 \\cdot 2\\pi R}{d}(\\varepsilon x + l - x),$$<br>тиймд $\\partial C/\\partial x = \\varepsilon_0 \\cdot 2\\pi R(\\varepsilon-1)/d$, иймд:<br>$$F_x = \\frac{U^2}{2}\\frac{\\partial C}{\\partial x} = \\frac{\\varepsilon_0(\\varepsilon-1)\\pi R U^2}{d}.$$"
        }
      ]
    },
    {
      "type": "problem",
      "number": "4.10",
      "title": "",
      "statement": [
        {
          "type": "text",
          "value": "Конденсатор нь хоёр хөдөлгөөнгүй хагас тойрог $R$ радиустай хавтан ба тэдгээрийн хооронд $O$ тэнхлэгийн эргэн тойронд эргэдэг $\\varepsilon$ диэлектрик тогтмолтой хавтгай диэлектрикаас тогтоно (Зураг 4.7). Хавтангийн зузаан $h$. Хавтануудад $U$ тогтмол хүчдэл байна. Зурагт үзүүлсэн байрлалд хөдөлгөөнт хавтанд $O$ тэнхлэгийн хавьтал хүчний моментийг ол."
        },
        {
          "type": "image",
          "src": "images/irodov-electromagnetism/3e870b25-6320-483d-9133-cdd5212c2707-119_250_304_312_166.jpg",
          "caption": "Зураг 4.7"
        }
      ],
      "solution": [
        {
          "type": "text",
          "value": "$\\alpha$ өнцгийн сектор талбай $S = \\alpha R^2/2$ болохоор:<br>$$C = \\frac{\\varepsilon_0\\alpha R^2}{2h} + \\frac{\\varepsilon\\varepsilon_0(\\pi-\\alpha)R^2}{2h},\\quad \\frac{\\partial C}{\\partial\\alpha} = \\frac{\\varepsilon_0 R^2(1-\\varepsilon)}{2h}.$$<br>(4.16)-аар:<br>$$N_z = \\frac{U^2}{2}\\frac{\\partial C}{\\partial\\alpha} = -(\\varepsilon-1)\\frac{\\varepsilon_0 R^2 U^2}{4h} < 0.$$<br>$N_z < 0$ нь момент цагийн зааны чиглэлтэй (диэлектрикийг дотогш татна) болохыг заана."
        }
      ]
    }
  ]
}