{
  "id": "3.6",
  "title": "3.6. Electromagnetic Induction. Maxwell's Equations",
  "body": [
    {
      "value": "## 3.6. ЦАХИЛГААН СОРОНЗОН ИНДУКЦИ. МАКСВЕЛЛИЙН ТЭГШИТГЭЛҮҮД\n\n- Фарадейгийн цахилгаан соронзон индукцийн хууль: $$\\mathscr{E}_{i}=-\\frac{d \\Phi}{d t} $$ - Соленоид ба тороид ороомгийн хувьд: $$\\Phi=N \\Phi_{1}, $$ энд $N$ нь ороодсын тоо, $\\Phi_{1}$ нь ороодол бүрээр нэвтрэх соронзон урсгал юм.\n- Соленоидын индукцлэл: $$L=\\mu \\mu_{0} n^{2} V . $$ - Гүйдлийн энерги ба хоёр гүйдлийн харилцан үйлчлэлийн энерги: $$W=\\frac{L I^{2}}{2}, \\quad W_{12}=L_{12} I_{1} I_{2} $$ - Соронзон орны энергийн эзлэхүүн нягт: $$w=\\frac{B^{2}}{2 \\mu \\mu_{0}}=\\frac{\\mathbf{B H}}{2} . $$ - Нүүлгэн шилжүүлэлтийн гүйдлийн нягт: $$\\mathbf{j}_{\\text{dis}}=\\frac{\\partial \\mathbf{D}}{\\partial t} . $$ - Максвеллийн тэгшитгэлүүд дифференциал хэлбэрээр: $\n\\begin{array}{ll}\n\\boldsymbol{\\nabla} \\times \\mathbf{E}=-\\frac{\\partial \\mathbf{B}}{\\partial t}, & \\boldsymbol{\\nabla} \\cdot \\mathbf{B}=0, \n\\boldsymbol{\\nabla} \\times \\mathbf{H}=\\mathbf{j}+\\frac{\\partial \\mathbf{D}}{\\partial t}, & \\boldsymbol{\\nabla} \\cdot \\mathbf{D}=\\rho, \n\\end{array}\n$ энд $\\boldsymbol{\\nabla} \\times \\equiv \\operatorname{rot}$ (ротор) ба $\\boldsymbol{\\nabla} \\cdot \\equiv \\operatorname{div}$ (дивергенц).\n- $v_{0}$ хурдтай хөдөлж буй $K$ системээс $K^{\\prime}$ систем рүү шилжихэд талбарын хувиргах томьёо. $v_{0} \\ll c$ үед: $$\\mathbf{E}^{\\prime}=\\mathbf{E}+[\\mathbf{v}_{0} \\mathbf{B}], \\quad \\mathbf{B}^{\\prime}=\\mathbf{B}-[\\mathbf{v}_{0} \\mathbf{E}] / c^{2} $$ Ерөнхий тохиолдолд: $\n\\begin{array}{ll}\n\\mathbf{E}_{\\|}^{\\prime}=\\mathbf{E}_{\\|}, & \\mathbf{B}_{\\|}^{\\prime}=\\mathbf{B}_{\\|},  \n\\mathbf{E}_{\\perp}^{\\prime}=\\frac{\\mathbf{E}_{\\perp}+[\\mathbf{v}_{0} \\mathbf{B}]}{\\sqrt{1-(v_{0} / c)^{2}}}, & B_{\\perp}^{\\prime}=\\frac{\\mathbf{B}_{\\perp}-[\\mathbf{v}_{0} \\mathbf{E}] / c^{2}}{\\sqrt{1-(v_{0} / c)^{2}}},\n\\end{array}\n$ энд $\\|$ ба $\\perp$ тэмдэглэгээ нь $\\mathbf{v}_{0}$ вектортой параллель ба перпендикуляр бүрдүүлэгчдийг илэрхийлнэ."
    },
    {
      "type": "problem",
      "number": "3.288",
      "title": "",
      "statement": [
        {
          "type": "text",
          "value": "$y=ax^2$ парабол хэлбэртэй муруй дамжуулагч утсан дээгүүр дамжуулагч холбогч саваа $t=0$ агшинд параболын оройноос эхлэн $w$ тогтмол хурдатгалтайгаар давшин хөдөлнө (3.78-р зураг). Систем нь $x, y$ хавтгайд перпендикуляр чиглэсэн $B$ индукцтэй нэгэн төрлийн соронзон оронд байрлана. Үүсэх хүрээний индукцийн ЦХХ-ийг $y$ өндрөөс хамааруулан ол."
        },
        {
          "type": "image",
          "src": "images/irodov-problems/c7fd2c75-af8b-4d89-bfbb-15bfd3e7201b-155_258_203_338_334.jpg",
          "caption": "Fig. 3.78."
        }
      ],
      "answer": [
        {
          "type": "text",
          "value": "$\\mathscr{E}_{i}=B y \\sqrt{8 w / a}$."
        }
      ]
    },
    {
      "type": "problem",
      "number": "3.289",
      "title": "",
      "statement": [
        {
          "type": "text",
          "value": "$l$ урттай дамжуулагч холбогч саваа бүхий тэгш өнцөгт хүрээ нь түүний хавтгайд перпендикуляр $B$ индукцтэй нэгэн төрлийн соронзон оронд байрлана (3.79-р зураг). Холбогч саваа $R$ эсэргүүцэлтэй бөгөөд хүрээний $AB$ ба $CD$ талууд харгалзан $R_1$ ба $R_2$ эсэргүүцэлтэй болно. Хүрээний өөрөө индукцийг тооцохгүйгээр холбогч $v$ тогтмол хурдтай хөдлөх үеийн түүгээр гүйх гүйдлийг ол."
        },
        {
          "type": "image",
          "src": "images/irodov-problems/c7fd2c75-af8b-4d89-bfbb-15bfd3e7201b-155_197_272_393_758.jpg",
          "caption": "Fig. 3.79."
        }
      ],
      "answer": [
        {
          "type": "text",
          "value": "$I=\\operatorname{Bvl} /\\left(R+R_{\\mu}\\right)$, энд $R_{\\mu}=R_{1} R_{2} /\\left(R_{1}+R_{2}\\right)$."
        }
      ]
    },
    {
      "type": "problem",
      "number": "3.290",
      "title": "",
      "statement": [
        {
          "type": "text",
          "value": "$a=25$ см радиустай металл диск өөрийн тэнхлэгийг тойрон $\\omega=130$ рад/с тогтмол өнцөг хурдтайгаар эргэлдэнэ. Дискний төв ба ирмэгийн хоорондох потенциалын зөрүүг дараах тохиолдолд ол:\n(а) гадаад соронзон орон байхгүй;\n(б) дискний хавтгайд перпендикуляр чиглэсэн $B=5.0$ мТл индукцтэй нэгэн төрлийн соронзон орон дотор."
        }
      ],
      "answer": [
        {
          "type": "text",
          "value": "(a) $\\Delta \\varphi=1 / 2 \\omega^{2} a^{2} m / e=3.0 \\mathrm{nV}$; (b) $\\Delta \\varphi \\approx 1 / 2 \\omega B a^{2}= =20 \\mathrm{mV}$."
        }
      ]
    },
    {
      "type": "problem",
      "number": "3.291",
      "title": "",
      "statement": [
        {
          "type": "text",
          "value": "$d=20$ см диаметртэй хагас тойрог хэлбэрийн нимгэн утсан хүрээ $B=5.0$ мТл индукцтэй нэгэн төрлийн соронзон оронд $\\\\omega = 100$ рад/с тогтмол өнцөг хурдтай эргэлдэнэ (энд $\\\\boldsymbol{\\\\omega} \\\\\\\\uparrow\\\\\\\\uparrow \\\\\\\\mathbf{B}$). Эргэлтийн тэнхлэг нь диаметрийнх нь нэг төгсгөлийг дайрна. Утсаар $A$ цэгээс $C$ цэг хүртэлх $\\\\int \\\\\\\\mathbf{E} d \\\\\\\\mathbf{r}$ шугаман интегралыг ол. Гарсан үр дүнгээ тайлбарла."
        }
      ],
      "answer": [
        {
          "type": "text",
          "value": "$\\int_{A}^{C} \\mathbf{E} d \\mathbf{r}=-1 / 2^{\\omega} \\omega d^{2}=-10 \\mathrm{mV}$."
        }
      ]
    },
    {
      "type": "problem",
      "number": "3.292",
      "title": "",
      "statement": [
        {
          "type": "text",
          "value": "$a$ радиустай хагас тойрог хэлбэрийн утсан хүрээ $B$ индукцтэй нэгэн төрлийн соронзон орны хил дээр байрлана (3.80-р зураг). $t=0$ агшинд $O$ тэнхлэгийг тойрон $\\\\beta$ тогтмол өнцөг хурдатгалтай эргэлдэж эхэлнэ. Хүрээнд үүсэх индукцийн ЦХХ-ийг $t$ хугацаанаас хамааруулан ол. Ойролцоо графикийг нь зур. Зураг дээрх сум ЦХХ-ний эерэг зүг харуулна."
        },
        {
          "type": "image",
          "src": "images/irodov-problems/c7fd2c75-af8b-4d89-bfbb-15bfd3e7201b-156_276_235_173_293.jpg",
          "caption": "Fig. 3.80."
        }
      ],
      "answer": [
        {
          "type": "text",
          "value": "$\\\\mathscr{E}_{i}=\\\\frac{1}{2}(-1)^{n} B a^2 \\\\beta t$, энд $n=1,2, \\\\dots$ нь тухайн $t$ агшны эргэлтийн дугаар. $\\\\mathscr{E}_{i}(t)$ график 25-р зурагт (хариуны хэсэгт) үзүүлсэн шиг байх бөгөөд энд $t_{n}=\\\\sqrt{2 \\\\pi n / \\\\beta}$ болно."
        }
      ]
    },
    {
      "type": "problem",
      "number": "3.293",
      "title": "",
      "statement": [
        {
          "type": "text",
          "value": "$I$ гүйдэлтэй урт шулуун дамжуулагч ба дамжуулагч холбогч саваа бүхий П-хэлбэрийн хүрээ нэг хавтгайд байрлана (3.81-р зураг). $l$ урт ба $R$ эсэргүүцэлтэй холбогч саваа баруун тийш $v$ тогтмол хурдтай гулсана. Холбогч саваанаас дамжуулагч утас хүртэлх зай $r$-ээс хамааруулан хүрээнд үүсэх индукцийн гүйдлийг ол. П-хэлбэрийн дамжуулагчийн эсэргүүцэл болон хүрээний өөрөө индукцийг тооцохгүй."
        }
      ],
      "answer": [
        {
          "type": "text",
          "value": "$I_{\\\\text{ind }}=\\\\alpha / r, $ энд $ \\\\alpha= \\\\mu_{0} l v I / 2 \\\\pi R$."
        }
      ]
    },
    {
      "type": "problem",
      "number": "3.294",
      "title": "",
      "statement": [
        {
          "type": "text",
          "value": "$a$ талтай квадрат хүрээ ба $I$ гүйдэлтэй урт шулуун утас нэг хавтгайд байрлана (3.82-р зураг). Хүрээ баруун тийш $v$ тогтмол хурдтай давшин хөдөлнө. Хүрээнд үүсэх индукцийн ЦХХ-ийг $x$ зайнаас хамааруулан ол."
        }
      ],
      "answer": [
        {
          "type": "text",
          "value": "$\\mathscr{E}_{i}=\\frac{\\mu_{0}}{4 \\pi} \\frac{2 I a^{2} v}{x(x+a)}$."
        }
      ]
    },
    {
      "type": "problem",
      "number": "3.295",
      "title": "",
      "statement": [
        {
          "type": "text",
          "value": "Металл саваа $a$ радиустай дамжуулагч цагираг дээгүүр гулсаж, $O$ хэвтээ тэнхлэгийг тойрон эргэлдэнэ (3.83-р зураг). Савааны масса $m$ болно. Систем нь цагирагийн хавтгайд перпендикуляр чиглэсэн $B$ индукцтэй нэгэн төрлийн соронзон оронд байрлана. Тэнхлэг ба цагираг нь эх үүсвэртэй холбогдож $R$ эсэргүүцэлтэй хэлхээг үүсгэнэ. Үрэлт, хэлхээний индукц болон цагирагийн эсэргүүцлийг тооцохгүйгээр савааг $\\\\omega$ тогтмол өнцөг хурдтайгаар эргүүлэхэд шаардагдах ЦХХ-ний өөрчлөгдөх хуулийг ол."
        },
        {
          "type": "image",
          "src": "images/irodov-problems/c7fd2c75-af8b-4d89-bfbb-15bfd3e7201b-156_327_266_811_792.jpg",
          "caption": "Fig. 3.83."
        }
      ],
      "answer": [
        {
          "type": "text",
          "value": "$\\mathscr{E}_{i}=\\frac{1}{2}\\left(\\omega a^{3} B^{3}+2 m g \\sin \\omega t\\right) / a B$."
        }
      ]
    },
    {
      "type": "problem",
      "number": "3.296",
      "title": "",
      "statement": [
        {
          "type": "text",
          "value": "$m$ масстай зэс холбогч саваа хэвтээ хавтгайд $\\\\alpha$ өнцөг үүсгэх хоёр зэрэгцээ зэс баар дээгүүр хүндийн хүчний нөлөөгөөр доош гулсана (3.84-р зураг). Бааруудын дээд үзүүрүүд $R$ эсэргүүцлээр холбогдсон бөгөөд тэдгээрийн хоорондох зай $l$ болно. Систем нь холбогчийн хөдөлгөөний хавтгайд перпендикуляр $B$ индукцтэй нэгэн төрлийн соронзон оронд байрлана. Баар, холбогч, болон контактын эсэргүүцэл, мөн хүрээний өөрөө индукцийг тооцохгүйгээр холбогчийн тогтворжсон хурдыг ол."
        },
        {
          "type": "image",
          "src": "images/irodov-problems/c7fd2c75-af8b-4d89-bfbb-15bfd3e7201b-157_264_253_216_271.jpg",
          "caption": "Fig. 3.84."
        }
      ],
      "answer": [
        {
          "type": "text",
          "value": "$v=\\frac{m g R \\sin \\alpha}{B^{2} l^{2}}$."
        }
      ]
    },
    {
      "type": "problem",
      "number": "3.297",
      "title": "",
      "statement": [
        {
          "type": "text",
          "value": "3.84-р зурагт үзүүлсэн системд $R$ эсэргүүцлийг $C$ багтаамжтай конденсатороор сольсон бол холбогчийн хурдатгалыг ол."
        },
        {
          "type": "image",
          "src": "images/irodov-problems/c7fd2c75-af8b-4d89-bfbb-15bfd3e7201b-157_264_253_216_271.jpg",
          "caption": "Fig. 3.84."
        }
      ],
      "answer": [
        {
          "type": "text",
          "value": "$w=\\frac{g \\sin \\alpha}{1+l^{2} B^{2} C / m}$."
        }
      ]
    },
    {
      "type": "problem",
      "number": "3.298",
      "title": "",
      "statement": [
        {
          "type": "text",
          "value": "$a$ радиустай хагас тойрог хэлбэрийн утсан хүрээ $B$ индукцтэй нэгэн төрлийн соронзон оронд $OO'$ тэнхлэгийг тойрон $\\\\omega$ тогтмол өнцөг хурдтайгаар эргэлдэнэ (3.85-р зураг). Эргэлтийн тэнхлэг нь соронзон орны чиглэлд перпендикуляр болно. Хэлхээний нийт эсэргүүцэл $R$ болно. Индукцийн гүйдлийн үүсгэх соронзон орныг тооцохгүйгээр нэг эргэлтийн хугацаанд хүрээнд ялгарах дулааны энергийн дундаж чадлыг ол."
        },
        {
          "type": "image",
          "src": "images/irodov-problems/c7fd2c75-af8b-4d89-bfbb-15bfd3e7201b-157_228_382_254_717.jpg",
          "caption": "Fig. 3.85."
        }
      ],
      "answer": [
        {
          "type": "text",
          "value": "$\\langle P\\rangle=\\frac{1}{2}\\left(\\pi \\omega a^{2} B\\right)^{2} / R$."
        }
      ]
    },
    {
      "type": "problem",
      "number": "3.299",
      "title": "",
      "statement": [
        {
          "type": "text",
          "value": "Цахилгаан соронзонгийн туйлуудын завсар руу тэнхлэг нь соронзон орны чиглэлтэй давхцаж байхаар жижиг ороомог байрлуулжээ. Ороомгийн хөндлөн огтлолын талбай $S = 3.0$ мм$^2$, ороодсын тоо $N = 60$ болно. Ороомгийг $180^\\\\circ$ эргүүлэхэд түүнд холбогдсон баллистик гальванометрээр $q = 4.5$ мкКл цэнэг гүйж өнгөрөв. Хэлхээний нийт эсэргүүцэл $R = 40$ Ом бол туйлуудын хоорондох соронзон индукцийг ол."
        }
      ],
      "answer": [
        {
          "type": "text",
          "value": "$B=\\frac{1}{2} q R / N S=0.5$ T."
        }
      ]
    },
    {
      "type": "problem",
      "number": "3.300",
      "title": "",
      "statement": [
        {
          "type": "text",
          "value": "$a$ тал бүхий квадрат утсан хүрээ ба $I$ тогтмол гүйдэлтэй шулуун дамжуулагч нэг хавтгайд байрлана (3.86-р зураг). Хүрээний өөрөө индукц $L$ ба эсэргүүцэл нь $R$ болно. Хүрээг дамжуулагчаас $b$ зайд орших $OO'$ тэнхлэгийг тойруулан $180^\\\\circ$ эргүүлжээ. Хүрээгээр гүйх цахилгаан цэнэгийг ол."
        },
        {
          "type": "image",
          "src": "images/irodov-problems/c7fd2c75-af8b-4d89-bfbb-15bfd3e7201b-157_273_356_1218_132.jpg",
          "caption": "Fig. 3.86."
        }
      ],
      "answer": [
        {
          "type": "text",
          "value": "$q=\\\\frac{\\\\mu_{0} a I}{2 \\\\pi R} \\\\ln \\\\frac{b+a}{b-a}$."
        },
        {
          "type": "image",
          "src": "images/irodov-problems/c7fd2c75-af8b-4d89-bfbb-15bfd3e7201b-325_323_370_269_860.jpg",
          "caption": "Зур. 25."
        },
        {
          "type": "text",
          "value": "3.301.\n(a) $I=\\frac{\\mu_{0} I_{0} v}{2 \\pi R} \\ln \\frac{b}{a}$;\n(b) $F=\\frac{v}{R}\\left(\\frac{\\mu_{0} I_{0}}{2 \\pi} \\ln \\frac{b}{a}\\right)^{2}$.\n3.302.\n(a) $s=v_{0} m R / l^{2} B^{2}$,\n(b) $Q=\\frac{1}{2} m v_{0}^{2}$."
        }
      ]
    },
    {
      "type": "problem",
      "number": "3.301",
      "title": "",
      "statement": [
        {
          "type": "text",
          "value": "$I_0$ тогтмол гүйдэлтэй урт шулуун утаснаас $a$ ба $b$ зайд түүнтэй параллель хоёр дамжуулагч баар байрлах бөгөөд тэдгээрийн үзүүрүүд $R$ эсэргүүцлээр холбогджээ (3.87-р зураг). Холбогч саваа бааруудын дагуу $v$ тогтмол хурдтайгаар үрэлтгүй гулсана. Утас, баар, холбогч болон контактын эсэргүүцэл, мөн хүрээний өөрөө индукцийг тооцохгүйгээр дараах зүйлсийг ол:\n(а) холбогч саваагаар гүйх индукцийн гүйдлийн хэмжээ ба чиглэл;\n(б) холбогчийг тогтмол хурдтай байлгахад шаардагдах хүч."
        },
        {
          "type": "image",
          "src": "images/irodov-problems/c7fd2c75-af8b-4d89-bfbb-15bfd3e7201b-157_242_611_1249_631.jpg",
          "caption": "Fig. 3.87."
        }
      ],
      "answer": [
        {
          "type": "text",
          "value": "(a) $I=\\frac{\\mu_{0} I_{0} v}{2 \\pi R} \\ln \\frac{b}{a}$; (b) $F=\\frac{v}{R}\\left(\\frac{\\mu_{0} I_{0}}{2 \\pi} \\ln \\frac{b}{a}\\right)^{2}$."
        }
      ]
    },
    {
      "type": "problem",
      "number": "3.302",
      "title": "",
      "statement": [
        {
          "type": "text",
          "value": "$m$ масстай дамжуулагч саваа $l$ зайтай хоёр зэрэгцээ металл баар дээгүүр үрэлтгүй гулсана (3.88-р зураг). Бааруудын зүүн үзүүрийг $R$ эсэргүүцлээр холбосон байна. Систем нь хүрээний хавтгайд перпендикуляр $B$ индукцтэй нэгэн төрлийн соронзон оронд байрлаж байна. $t=0$ агшинд $AB$ саваанд $v_0$ анхны хурд өгч баруун тийш хөдөлгөв. Баар болон савааны эсэргүүцэл, мөн өөрөө индукцийг тооцохгүйгээр дараах зүйлсийг ол:\n(а) саваа зогсох хүртэлх зам;\n(б) энэ явцад $R$ эсэргүүцэл дээр ялгарах дулааны хэмжээ."
        },
        {
          "type": "image",
          "src": "images/irodov-problems/c7fd2c75-af8b-4d89-bfbb-15bfd3e7201b-158_221_329_727_301.jpg",
          "caption": "Fig. 3.88."
        }
      ],
      "answer": [
        {
          "type": "text",
          "value": "(a) $s=v_{0} m R / l^{2} B^{2}$, (b) $Q=\\frac{1}{2} m v_{0}^{2}$."
        }
      ]
    },
    {
      "type": "problem",
      "number": "3.303",
      "title": "",
      "statement": [
        {
          "type": "text",
          "value": "$AB$ холбогч саваа хэвтээ хавтгайд орших П-хэлбэрийн дамжуулагч хүрээ дээгүүр үрэлтгүй гулсана (3.89-р зураг). Холбогч саваа $l$ урттай, $m$ масстай, $R$ эсэргүүцэлтэй болно. Систем бүхэлдээ босоо чиглэлтэй $B$ индукцтэй нэгэн төрлийн соронзон оронд байрлана. $t=0$ агшинд холбогч саваанд тогтмол $F$ хэвтээ хүч үйлчилж баруун тийш хөдөлж эхэлсэн бол түүний хурд хугацаанаас хамаарч хэрхэн өөрчлөгдөхийг ол. Хүрээний өөрөө индукц болон П-хэлбэрийн дамжуулагчийн эсэргүүцлийг тооцохгүй."
        },
        {
          "type": "image",
          "src": "images/irodov-problems/c7fd2c75-af8b-4d89-bfbb-15bfd3e7201b-158_221_297_721_768.jpg",
          "caption": "Fig. 3.89."
        }
      ],
      "answer": [
        {
          "type": "text",
          "value": "$v = \\\\frac{F}{\\\\alpha m} (1 - \\\\mathrm{e}^{-\\\\alpha t})$, энд $\\\\alpha = B^2 l^2 / m R$."
        }
      ]
    },
    {
      "type": "problem",
      "number": "3.304",
      "title": "",
      "statement": [
        {
          "type": "text",
          "value": "3.90-р зурагт нэгэн төрлийн соронзон оронд байрлах нимгэн дамжуулагчаар хийсэн хавтгай дүрсүүдийг үзүүлэв. Соронзон орон уншигчаас цааш, зургийн хавтгайд перпендикуляр чиглэсэн бөгөөд индукц нь буурч эхэлсэн бол эдгээр хүрээнүүдэд үүсэх индукцийн гүйдлийн чиглэлийг ол."
        }
      ],
      "answer": [
        {
          "type": "text",
          "value": "(а) дугуй дамжуулагчаар гүйдэл цагны зүүний дагуу гүйх бөгөөд холбогчоор гүйдэл гүйхгүй; (б) гадна хүрээгээр цагны зүүний дагуу; (в) хоёр дугуй хүрээгээр хоёулангаар нь цагны зүүний дагуу гүйх бөгөөд холбогчоор гүйдэл гүйхгүй; (г) «наймын тоо»-ны зүүн гар талын хэсгээр цагны зүүний дагуу гүйнэ."
        }
      ]
    },
    {
      "type": "problem",
      "number": "3.305",
      "title": "",
      "statement": [
        {
          "type": "text",
          "value": "3.91-р зурагт үзүүлсэн хавтгай хүрээ нь $a=20$ см ба $b=10$ см тал бүхий хоёр квадрат хэсгээс тогтох бөгөөд түүний хавтгайд перпендикуляр чиглэсэн нэгэн төрлийн соронзон оронд байрлана. Соронзон индукц хугацаанаас хамаарч $B=B_0 \\\\sin \\\\omega t$ хуулиар хэлбэлзэх бөгөөд энд $B_0=10$ мТл, $\\\\omega=100$ с$ ^{-1}$ болно. Дамжуулагч утасны нэгж уртын эсэргүүцэл $\\\\rho=50$ мОм/м бол хүрээнд үүсэх гүйдлийн далайцыг ол. Хүрээний өөрөө индукцийг тооцохгүй."
        }
      ],
      "answer": [
        {
          "type": "text",
          "value": "$I= \\\\omega B_{0} (a^2 - b^2) / 8(a+b) \\\\rho = \\\\omega B_{0} (a-b) / 8 \\\\rho = 0.5$ А."
        }
      ]
    },
    {
      "type": "problem",
      "number": "3.306",
      "title": "",
      "statement": [
        {
          "type": "text",
          "value": "$N$ маш олон ороодол бүхий хавтгай спираль түүний хавтгайд перпендикуляр нэгэн төрлийн соронзон оронд байрлаж байна. Спиралийн гадна талын ороодсын радиус $a$ болно. Соронзон индукц $B=B_0 \\\\sin \\\\omega t$ хуулиар өөрчлөгдөх ($B_0$ ба $\\\\omega$ - тогтмол) бол спиральд үүсэх индукцийн ЦХХ-ний далайцыг ол."
        }
      ],
      "answer": [
        {
          "type": "text",
          "value": "$\\mathscr{E}_{i m}=1 / 3 \\pi a^{2} N \\omega B_{0}$."
        }
      ]
    },
    {
      "type": "problem",
      "number": "3.307",
      "title": "",
      "statement": [
        {
          "type": "text",
          "value": "П-хэлбэрийн дамжуулагч хүрээ түүний хавтгайд перпендикуляр $B$ индукцтэй нэгэн төрлийн соронзон оронд байрлах бөгөөд соронзон индукц $\\\\dot{B}=0.10$ Тл/с хурдтайгаар өөрчлөгдөнө. Дамжуулагч холбогч саваа бааруудын дагуу $w=10$ см/с$^2$ хурдатгалтайгаар хөдөлж эхлэв. Холбогчийн урт $l=20$ см болно. Хэрэв $t=0$ агшинд хүрээний талбай болох соронзон индукц тэг байсан бол хөдөлгөөн эхэлснээс хойш $t=2.0$ с-ийн дараах хүрээнд үүсэх индукцийн ЦХХ-ийг ол. Хүрээний өөрөө индукцийг тооцохгүй."
        }
      ],
      "answer": [
        {
          "type": "text",
          "value": "$\\mathscr{E}_{i}=3 / 2 w l \\dot{B} t^{2}=12 \\mathrm{mV}$."
        }
      ]
    },
    {
      "type": "problem",
      "number": "3.308",
      "title": "",
      "statement": [
        {
          "type": "text",
          "value": "$a$ радиустай хөндлөн огтлол бүхий урт шулуун соленоидын нэгж уртад ногдох ороодсын тоо $n$ бөгөөд түүгээр гүйх гүйдэл $\\\\dot{I}$ А/с тогтмол хурдтайгаар өөрчлөгдөнө. Соленоидын тэнхлэгээс $r$ зайд орших индукцийн цахилгаан орны хүчлэгийг ол. Энэ хамаарлын ойролцоо графикийг зур."
        }
      ],
      "answer": [
        {
          "type": "text",
          "value": "$E=\\left\\{\\begin{array}{l}1 / 2 \\mu_{0} n \\dot{I} r \\text { үед } r<a,\n1 / 2 \\mu_{0} n \\dot{I} a^{2} / r \\text { үед } r>a.\\end{array}\\right.$"
        }
      ]
    },
    {
      "type": "problem",
      "number": "3.309",
      "title": "",
      "statement": [
        {
          "type": "text",
          "value": "$d=5$ см диаметртэй хөндлөн огтлол бүхий урт шулуун соленоид дээр $n=20$ ороодол/см нягттай нэг ороодол бүхий $S=1.0$ мм$^2$ хөндлөн огтлолтой зэс утсан хүрээг соленоидын ороомогтой нягт байхаар байрлуулав. Хэрэв соленоидын ороодсоор гүйх гүйдэл $\\\\dot{I}=100$ А/с тогтмол хурдтайгаар нэмэгдэх бол хүрээнд үүсэх гүйдлийг ол. Хүрээний өөрөө индукцийг тооцохгүй."
        }
      ],
      "answer": [
        {
          "type": "text",
          "value": "$I = 1/4 \\\\mu_0 n S d \\\\dot{I} / \\\\rho = 2$ мА, энд $\\\\rho$ нь зэсийн хувийн эсэргүүцэл болно."
        }
      ]
    },
    {
      "type": "problem",
      "number": "3.310",
      "title": "",
      "statement": [
        {
          "type": "text",
          "value": "$a$ радиустай хөндлөн огтлол бүхий урт соленоид дээр нимгэн тусгаарлагчтай утсаар хийсэн цагираг зүүжээ. Цагирагны нэг хагасын эсэргүүцэл нөгөө хагасынхаа эсэргүүцлээс $\\\\eta$ дахин их болно. Соленоидын үүсгэх соронзон индукц $B=bt$ хуулиар өөрчлөгдөх ($b$ - тогтмол) бол цагираг доторх цахилгаан орны хүчлэгийн хэмжээг ол."
        }
      ],
      "answer": [
        {
          "type": "text",
          "value": "$E=1 / 2 a b(\\eta-1) /(\\eta+1)$."
        }
      ]
    },
    {
      "type": "problem",
      "number": "3.311",
      "title": "",
      "statement": [
        {
          "type": "text",
          "value": "$q$ цэнэг бүхий $m$ масстай нимгэн дамжуулагч бус цагираг өөрийн тэнхлэгийг тойрон чөлөөтэй эргэлдэх боломжтой. Эхлээд цагираг тайван байсан бөгөөд соронзон орон байхгүй байв. Дараа нь цагирагийн хавтгайд перпендикуляр бараг нэгэн төрлийн соронзон орныг зарим нэг хуулийн дагуу $\\\\mathbf{B}(t)$ болтол нэмэгдүүлжээ. Цагирагийн $\\\\omega$ өнцөг хурдыг $B(t)$ индукцээс хамааруулан ол."
        }
      ],
      "answer": [
        {
          "type": "text",
          "value": "$\\omega=-\\frac{q}{2 m} \\mathbf{B}(t)$."
        }
      ]
    },
    {
      "type": "problem",
      "number": "3.312",
      "title": "",
      "statement": [
        {
          "type": "text",
          "value": "$a$ радиустай, $r$ эсэргүүцэлтэй нимгэн утсан цагираг $l$ урттай, $b$ радиустай урт соленоидын дотор тэнхлэгүүд нь давхцаж байхаар байрлана. Соленоидыг $V$ тогтмол хүчдэлтэй эх үүсвэрт холбов. Соленоидын хэлхээний нийт эсэргүүцэл $R$ бол цагирагийн уртын нэгжид үйлчлэх радиаль хүчний хамгийн их утгыг ол. Цагирагны өөрөө индукцийг тооцохгүй."
        }
      ],
      "answer": [
        {
          "type": "text",
          "value": "$F_{1 \\max }=\\frac{\\mu_{0} a^{2} V^{2}}{4 r R l b^{2}}$."
        }
      ]
    },
    {
      "type": "problem",
      "number": "3.313",
      "title": "",
      "statement": [
        {
          "type": "text",
          "value": "$r$ эсэргүүцэлтэй хөдөлгөөнгүй хүрээгээр нэвтрэх соронзон урсгал $\\\\tau$ хугацааны завсарт $\\\\Phi = at(\\\\tau - t)$ хуулиар өөрчлөгдөнө. Энэ хугацаанд хүрээнд ялгарах дулааны хэмжээг ол. Хүрээний өөрөө индукцийг тооцохгүй."
        }
      ],
      "answer": [
        {
          "type": "text",
          "value": "$Q=1 / 3 a^{2} \\tau^{3} / R$."
        }
      ]
    },
    {
      "type": "problem",
      "number": "3.314",
      "title": "",
      "statement": [
        {
          "type": "text",
          "value": "Урт соленоидын дунд хэсэгт $\\\\rho$ хувийн эсэргүүцэлтэй дамжуулагч материалаар хийсэн, квадрат хөндлөн огтлолтой коаксиаль цагираг байрлана. Цагирагны зузаан $h$ бөгөөд дотор ба гадна радиусуд нь харгалзан $a$ ба $b$ болно. Соленоидын үүсгэх соронзон индукц хугацаанаас хамаарч $B = \\\\beta t$ ($ \\\\beta$ - тогтмол) хуулиар өөрчлөгдөх бол цагирагт үүсэх индукцийн гүйдлийг ол. Цагирагны өөрөө индукцийг тооцохгүй."
        }
      ],
      "answer": [
        {
          "type": "text",
          "value": "$I=1 / 4\\left(b^{2}-a^{2}\\right) \\beta h / \\rho$."
        }
      ]
    },
    {
      "type": "problem",
      "number": "3.315",
      "title": "",
      "statement": [
        {
          "type": "text",
          "value": "Хэрэв соленоидын хөндлөн огтлолын диаметр нь түүний уртаас хамаагүй бага бол $l_0 = 100$ см урттай, $L = 1.0$ мГн индукцлэлтэй соленоид орооход хэдэн метр нимгэн утас шаардлагатай вэ?"
        }
      ],
      "answer": [
        {
          "type": "text",
          "value": "$l=\\sqrt{4 \\pi l_{0} L / \\mu_{0}}=0.10 \\mathrm{~кm}$."
        }
      ]
    },
    {
      "type": "problem",
      "number": "3.316",
      "title": "",
      "statement": [
        {
          "type": "text",
          "value": "$l$ урттай, $R$ эсэргүүцэлтэй, $m$ масстай зэс утсаар ороосон урт соленоидын индукцлэлийг ол. Соленоидын диаметр нь түүний уртаас хамаагүй бага гэж үзнэ."
        }
      ],
      "answer": [
        {
          "type": "text",
          "value": "$L = \\\\frac{\\\\mu_0}{4 \\\\pi} \\\\frac{mR}{l \\\\rho \\\\rho_0}$, энд $\\\\rho$ ба $\\\\rho_0$ нь зэсийн хувийн эсэргүүцэл ба нягт болно."
        }
      ]
    },
    {
      "type": "problem",
      "number": "3.317",
      "title": "",
      "statement": [
        {
          "type": "text",
          "value": "$L = 300$ мГн индукцлэлтэй, $R = 140$ мОм эсэргүүцэлтэй ороомгийг тогтмол хүчдэлтэй эх үүсвэрт холбов. Ороомгоор гүйх гүйдэл тогтворжсон утгынхаа $\\\\eta = 50\\%$-д хүртэл ямар хугацаа өнгөрөх вэ?"
        }
      ],
      "answer": [
        {
          "type": "text",
          "value": "$t=-\\frac{L}{R} \\ln (1-\\eta)=1.5 \\mathrm{~с}$."
        }
      ]
    },
    {
      "type": "problem",
      "number": "3.318",
      "title": "",
      "statement": [
        {
          "type": "text",
          "value": "$l = 1.0$ м урттай, $m = 1.0$ кг масстай зэс утсаар нэг үе ороосон урт шулуун соленоидын $\\\\tau$ хугацааны тогтмолыг тооцоол. Соленоидын диаметр нь түүний уртаас хамаагүй бага гэж үзнэ. Санамж: Хугацааны тогтмол $\\\\tau$ нь $L/R$ харьцаа бөгөөд $L$ нь индукцлэл, $R$ нь эсэргүүцэл юм."
        }
      ],
      "answer": [
        {
          "type": "text",
          "value": "$\\tau = \\\\frac{\\\\mu_0}{4 \\\\pi} \\\\frac{m}{l \\\\rho \\\\rho_0} = 0.7$ мс, энд $\\\\rho$ нь зэсийн хувийн эсэргүүцэл, $\\\\rho_0$ нь нягт болно."
        }
      ]
    },
    {
      "type": "problem",
      "number": "3.319",
      "title": "",
      "statement": [
        {
          "type": "text",
          "value": "Хоёр нимгэн ханатай коаксиаль металл цилиндрээс бүрдэх кабелийн нэгж уртын индукцлэлийг ол. Гадна цилиндрийн радиус нь дотор цилиндрийн радиусаас $\\\\eta = 3.6$ дахин их, цилиндрүүдийн хоорондох орчны соронзон нэвтрүүлэх чадвар $\\\\mu = 1$ болно."
        }
      ],
      "answer": [
        {
          "type": "text",
          "value": "$L_{1}=\\frac{\\mu \\mu_{0}}{2 \\pi} \\ln \\eta=0.26 \\mu \\mathrm{H} / \\mathrm{м}$."
        }
      ]
    },
    {
      "type": "problem",
      "number": "3.320",
      "title": "",
      "statement": [
        {
          "type": "text",
          "value": "Дотор радиус нь $b$, хөндлөн огтлол нь $a$ талтай квадрат хэлбэртэй тороид ороомгийн индукцлэлийг ол. Ороомог нь $N$ ороодолтой бөгөөд доторх орон зай нь $\\\\mu$ соронзон нэвтрүүлэх чадвартай нэгэн төрлийн парамагнитаар дүүргэгдсэн байна."
        }
      ],
      "answer": [
        {
          "type": "text",
          "value": "$L=\\frac{\\mu_{0}}{2 \\pi} \\mu N^{2} a \\ln \\left(1+\\frac{a}{b}\\right)$."
        }
      ]
    },
    {
      "type": "problem",
      "number": "3.321",
      "title": "",
      "statement": [
        {
          "type": "text",
          "value": "Хоёр зэрэгцээ дамжуулагч туузны нэгж уртын индукцлэлийг ол (3.92-р зураг). Туузуудын хоорондох зай $h$ нь тэдгээрийн өргөн $b$-ээс хамаагүй бага, жишээ нь $b/h = 50$ болно."
        },
        {
          "type": "image",
          "src": "images/irodov-problems/c7fd2c75-af8b-4d89-bfbb-15bfd3e7201b-161_270_482_197_752.jpg",
          "caption": "Fig. 3.92."
        }
      ],
      "answer": [
        {
          "type": "text",
          "value": "$L_{1}=\\mu_{0} h / b=25 \\mathrm{nH} / \\mathrm{м}$."
        }
      ]
    },
    {
      "type": "problem",
      "number": "3.322",
      "title": "",
      "statement": [
        {
          "type": "text",
          "value": "Хоёр зэрэгцээ утастай шугамын нэгж уртын индукцлэлийг ол. Утас бүрийн радиус нь тэдгээрийн тэнхлэгүүд хоорондын зайнаас $\\\\eta$ дахин бага ($\\\\eta \\\\gg 1$) болно. Утасны доторх соронзон орныг тооцохгүй, орчны соронзон нэвтрүүлэх чадвар $\\\\mu = 1$ болно."
        }
      ],
      "answer": [
        {
          "type": "text",
          "value": "$L_{1} \\approx \\frac{\\mu_{0}}{\\pi} \\ln \\eta$."
        }
      ]
    },
    {
      "type": "problem",
      "number": "3.323",
      "title": "",
      "statement": [
        {
          "type": "text",
          "value": "$L$ индукцлэлтэй, $a$ радиустай хэт дамжуулагч цагираг $B$ индукцтэй нэгэн төрлийн соронзон оронд байрлана. Цагирагны хавтгай $\\\\mathbf{B}$ вектортой параллель байсан бөгөөд цагираг дахь гүйдэл тэг байв. Дараа нь цагирагийг хавтгай нь орны чиглэлд перпендикуляр болтол $90^\\\\circ$ эргүүлжээ. Дараах зүйлсийг ол:\n(а) эргэлтийн дараа цагирагт үүссэн индукцийн гүйдэл;\n(б) эргэлтийн үед гүйцэтгэсэн ажил."
        }
      ],
      "answer": [
        {
          "type": "text",
          "value": "(a) $I=\\pi a^{2} B / L$; (b) $A=1 /{ }_{2} \\pi^{2} a^{4} B^{2} / L$."
        }
      ]
    },
    {
      "type": "problem",
      "number": "3.324",
      "title": "",
      "statement": [
        {
          "type": "text",
          "value": "Хэт дамжуулагч утсаар ороосон урт соленоидоор $I_0 = 1.9$ А гүйдэл гүйнэ. Соленоидын уртыг $\\\\eta = 5\\%$ -иар нэмэгдүүлсэн бол түүгээр гүйх гүйдлийг ол."
        }
      ],
      "answer": [
        {
          "type": "text",
          "value": "$I=I_{0}(1+\\eta)=2 \\mathrm{~А}$."
        }
      ]
    },
    {
      "type": "problem",
      "number": "3.325",
      "title": "",
      "statement": [
        {
          "type": "text",
          "value": "$b=1.0 \\mathrm{~мм}$ радиустай нимгэн утсаар хийсэн $a=50 \\mathrm{~мм}$ радиустай цагираг нь $B=0.50 \\mathrm{mT}$ индукц бүхий жигд соронзон орон дотор байрласан тул цагирагийн хавтгай нь $\\mathbf{B}$ векторт перпендикуляр байв. Дараа нь цагиргийг хэт дамжуулагч төлөвт хөргөж, соронзон орныг унтраасан. Үүний дараа цагирагийн гүйдлийг ол. Гадаргуугийн гүйдэл урсах нимгэн цагирагийн индукц нь $L=\\mu_{0} a\\left(\\ln \\frac{8 a}{b}-2\\right)$ -тэй тэнцүү болохыг анхаарна уу."
        }
      ],
      "answer": [
        {
          "type": "text",
          "value": "$I=\\frac{\\pi a B}{\\mu_{0}\\left(\\ln \\frac{8 a}{b}-2\\right)}=50 \\mathrm{~А}$."
        }
      ]
    },
    {
      "type": "problem",
      "number": "3.326",
      "title": "",
      "statement": [
        {
          "type": "text",
          "value": "Тогтмол $\\\\mathscr{E}$ ЦХХ-тэй эх үүсвэр ба $L$ индукцлэлтэй ороомог цуваа холбогдсон битүү хэлхээний нийт идэвхтэй эсэргүүцэл $R$ болно. $t=0$ агшинд ороомгийн индукцлэл $\\\\eta$ дахин огцом буурав. Хэлхээний гүйдлийг $t$ хугацаанаас хамааруулан ол. Заавар: Индукцлэл үсрэлттэйгээр өөрчлөгдөхөд соронзон урсгал (урсгал холболт) хадгалагдана."
        }
      ],
      "answer": [
        {
          "type": "text",
          "value": "$I=\\frac{\\mathscr{C}}{R}\\left[1+(\\eta-1) \\mathrm{e}^{-t \\eta R / L}\\right]$."
        }
      ]
    },
    {
      "type": "problem",
      "number": "3.327",
      "title": "",
      "statement": [
        {
          "type": "text",
          "value": "3.93-р зурагт үзүүлсэн хэлхээний $Sw$ түлхүүрийг $t=0$ агшинд залгасны дараа $L$ индукцлэлээр гүйх гүйдлийн хугацааны хамаарлыг ол."
        }
      ],
      "answer": [
        {
          "type": "text",
          "value": "$I=\\frac{\\mathscr{E}}{R}\\left(1-\\mathrm{e}^{-t R / 2 L}\\right)$."
        }
      ]
    },
    {
      "type": "problem",
      "number": "3.328",
      "title": "",
      "statement": [
        {
          "type": "text",
          "value": "3.94-р зурагт үзүүлсэн хэлхээнд $\\\\mathscr{E}$ ЦХХ, $R$ эсэргүүцэл, $L_1$ ба $L_2$ индукцлэлүүд өгөгджээ. Эх үүсвэр ба ороомгуудын эсэргүүцлийг тооцохгүй. $Sw$ түлхүүрийг залгасны дараа ороомгуудаар гүйх тогтворжсон гүйдлүүдийг ол."
        },
        {
          "type": "image",
          "src": "images/irodov-problems/c7fd2c75-af8b-4d89-bfbb-15bfd3e7201b-162_266_270_165_772.jpg",
          "caption": "Fig. 3.94."
        }
      ],
      "answer": [
        {
          "type": "text",
          "value": "$I_{1}=\\frac{\\mathscr{E} L_{2}}{R\\left(L_{1}+L_{2}\\right)}, I_{2}=\\frac{\\mathscr{E} L_{1}}{R\\left(L_{1}+L_{2}\\right)}$."
        }
      ]
    },
    {
      "type": "problem",
      "number": "3.329",
      "title": "",
      "statement": [
        {
          "type": "text",
          "value": "Урт шулуун утас ба $a$ ба $b$ талтай тэгш өнцөгт хүрээний харилцан индукцийг тооцоол. Хүрээ ба утас нь хэвтэж байна\nижил хавтгайд, $b$ тал нь утсанд хамгийн ойр байх ба түүнээс $l$ зайгаар тусгаарлагдаж, түүнтэй параллель чиглэнэ."
        }
      ],
      "answer": [
        {
          "type": "text",
          "value": "$L_{12}=\\frac{\\mu_{0} b}{2 \\pi} \\ln \\left(1+\\frac{a}{l}\\right)$."
        }
      ]
    },
    {
      "type": "problem",
      "number": "3.330",
      "title": "",
      "statement": [
        {
          "type": "text",
          "value": "Тороид ороомог болон түүний тэнхлэгээр дайрсан хязгааргүй шулуун утасны харилцан индукцлэлийг ол. Ороомог нь тэгш өнцөгт (квадрат) хөндлөн огтлолтой, дотор радиус нь $a$, гадна радиус нь $b$ болно. Утастай параллель орших тороидын хөндлөн огтлолын тал $h$ байх бөгөөд ороомог нь $N$ ороодолтой болно. Систем $\\\\mu$ соронзон нэвтрүүлэх чадвартай нэгэн төрлийн соронзон орчинд байрлана."
        }
      ],
      "answer": [
        {
          "type": "text",
          "value": "$L_{12}=\\frac{\\mu_{0} \\mu h N}{2 \\pi} \\ln \\frac{b}{a}$.\n3.331.\n(a) $L_{12} \\approx 1 /{ }_{2} \\mu_{0} \\pi a^{2} / b$;\n(b) $\\Phi_{21}=1 / 2 \\mu_{0} \\pi a^{2} I / b$."
        }
      ]
    },
    {
      "type": "problem",
      "number": "3.331",
      "title": "",
      "statement": [
        {
          "type": "text",
          "value": "$a$ ба $b$ радиустай дугуй хэлбэртэй нимгэн коаксиаль (төвлөрсөн) хоёр хүрээ нэг хавтгайд байрлана. $a \\\\ll b$ гэж үзээд дараах зүйлсийг ол:\n(а) тэдгээрийн харилцан индукцлэл;\n(б) дотоод хүрээгээр $I$ гүйдэл гүйх үед гадна хүрээгээр нэвтрэх соронзон урсгал."
        }
      ],
      "answer": [
        {
          "type": "text",
          "value": "(a) \\(L_{12} \\approx 1 /{ }_{2} \\mu_{0} \\pi a^{2} / b\\); (b) \\(\\Phi_{21}=1 / 2 \\mu_{0} \\pi a^{2} I / b\\)."
        }
      ]
    },
    {
      "type": "problem",
      "number": "3.332",
      "title": "",
      "statement": [
        {
          "type": "text",
          "value": "Жижиг цилиндр соронзон $M$ (3.95-р зураг) $N$ ороодолтой, $a$ радиустай нимгэн ороомгийн төвд байрлана. Ороомог нь баллистик гальванометртэй холбогдсон бөгөөд хэлхээний нийт эсэргүүцэл $R$ болно. Соронзыг ороомгоос холдуулахад гальванометрээр $q$ цэнэг гүйж өнгөрсөн бол соронзны соронзон моментийг ол."
        },
        {
          "type": "image",
          "src": "images/irodov-problems/c7fd2c75-af8b-4d89-bfbb-15bfd3e7201b-162_129_480_1386_269.jpg",
          "caption": "Fig. 3.95."
        }
      ],
      "answer": [
        {
          "type": "text",
          "value": "$p_{m}=2 a R q / \\mu_{0} N$."
        }
      ]
    },
    {
      "type": "problem",
      "number": "3.333",
      "title": "",
      "statement": [
        {
          "type": "text",
          "value": "$a$ радиустай хоёр ижил нимгэн коаксиаль хүрээний төвүүд хоорондоо $l$ зайд оршино. $l \\\\gg a$ үеийн харилцан индукцлэлийн ойролцоо томьёог ол."
        }
      ],
      "answer": [
        {
          "type": "text",
          "value": "$L_{12} \\approx 1 / 2 \\mu_{0} \\pi a^{4} / l^{3}$."
        }
      ]
    },
    {
      "type": "problem",
      "number": "3.334",
      "title": "",
      "statement": [
        {
          "type": "text",
          "value": "Харилцан индукцлэл нь $L_{12}$ байх хоёр хөдөлгөөнгүй хүрээ байрлана. Нэгдүгээр хүрээний гүйдэл $I_1 = \\\\alpha t$ ($ \\\\alpha$ - тогтмол) хуулиар өөрчлөгдөж эхлэв. $L_2$ индукцлэлтэй, $R$ эсэргүүцэлтэй хоёрдугаар хүрээнд үүсэх индукцийн гүйдэл $I_2$ хугацаанаас хэрхэн хамаарахыг ол."
        }
      ],
      "answer": [
        {
          "type": "text",
          "value": "$I_{2}=\\frac{\\alpha L_{12}}{R}\\left(1-\\mathrm{e}^{-t R / L_{2}}\\right)$."
        }
      ]
    },
    {
      "type": "problem",
      "number": "3.335",
      "title": "",
      "statement": [
        {
          "type": "text",
          "value": "$L = 2.0$ мГн индукцлэлтэй, $R = 1.0$ Ом эсэргүүцэлтэй ороомгийг $\\\\mathscr{E} = 3.0$ В ЦХХ-тэй эх үүсвэрт холбов (3.96-р зураг). Ороомогтой $R_0 = 2.0$ Ом эсэргүүцлийг зэрэгцээ залгажээ. $Sw$ түлхүүрийг салгасны дараа ороомогт ялгарах дулааны хэмжээг ол. Эх үүсвэрийн дотоод эсэргүүцлийг тооцохгүй."
        },
        {
          "type": "image",
          "src": "images/irodov-problems/c7fd2c75-af8b-4d89-bfbb-15bfd3e7201b-162_251_219_1284_872.jpg",
          "caption": "Fig. 3.96."
        }
      ],
      "answer": [
        {
          "type": "text",
          "value": "$Q=\\frac{L g^{2}}{2 R^{2}\\left(1+R_{0} / R\\right)}=3 \\mu \\mathrm{~Ж}$."
        }
      ]
    },
    {
      "type": "problem",
      "number": "3.336",
      "title": "",
      "statement": [
        {
          "type": "text",
          "value": "Ган тороид ороомог $N = 500$ ороодолтой болно. Ороодсоор $I = 2.0$ А гүйдэл гүйхэд тороидын хөндлөн огтлолын талбайгаар нэвтрэх соронзон урсгал $\\\\Phi = 1.0$ мВб бол соронзон орны энергийг ол."
        }
      ],
      "answer": [
        {
          "type": "text",
          "value": "$Вт=1 /{ }_{2} N \\Phi I=0.5 \\mathrm{~Ж}$."
        }
      ]
    },
    {
      "type": "problem",
      "number": "3.337",
      "title": "",
      "statement": [
        {
          "type": "text",
          "value": "$a = 3.0$ см радиустай дугуй хөндлөн огтлолтой, ган зүрхэвчтэй тороид ороомог $N = 1000$ ороодолтой бөгөөд түүгээр $I = 1.0$ А гүйдэл гүйнэ. Тороидын дундаж радиус $b = 32$ см болно. 3.76-р зурагт үзүүлсэн графикийг ашиглан зүрхэвч доторх соронзон орны энергийг ол. Соронзон орны хүчлэг $H$-ийг хөндлөн огтлол даяар ижил бөгөөд түүний төв дэх утгатайгаа тэнцүү гэж үзнэ."
        }
      ],
      "answer": [
        {
          "type": "text",
          "value": "$Вт=B H \\\\pi^{2} a^{2} b=2.0 \\\\mathrm{~Ж}$, энд $H=\\\\frac{1}{2} N I / \\\\pi b$.\n3.338.\n(a) $W_{g a p} / W_{m} \\approx \\mu b / \\pi d=3.0$;\n(b) $L \\approx \\frac{\\mu_{0} S N^{2}}{b+\\pi d / \\mu}=0.15 \\mathrm{H}$."
        }
      ]
    },
    {
      "type": "problem",
      "number": "3.338",
      "title": "",
      "statement": [
        {
          "type": "text",
          "value": "Ферросоронзон материалаар хийсэн нимгэн цагираг $d = 30$ см дундаж диаметртэй, $N = 800$ ороодолтой болно. Цагирагны хөндлөн огтлолын талбай $S = 5.0$ см$^2$ бөгөөд түүнд $b = 2.0$ мм өргөнтэй агаарын завсар гаргажээ. Гүйдэл гүйх үед соронзон нэвтрүүлэх чадвар $\\\\mu = 1400$ байсан бол дараах зүйлсийг ол:\n(а) агаарын завсар дахь энерги болон ферросоронзон зүрхэвч доторх энергийн харьцаа;\n(б) системийн индукцлэлийг хоёр аргаар (соронзон урсгалаар ба энергээр) ол."
        }
      ],
      "answer": [
        {
          "type": "text",
          "value": "(a) $W_{g a p} / W_{m} \\approx \\mu b / \\pi d=3.0$; (b) $L \\approx \\frac{\\mu_{0} S N^{2}}{b+\\pi d / \\mu}=0.15 \\mathrm{H}$."
        }
      ]
    },
    {
      "type": "problem",
      "number": "3.339",
      "title": "",
      "statement": [
        {
          "type": "text",
          "value": "Гадаргуудаа жигд цэнэглэгдсэн урт цилиндр өөрийн тэнхлэгийг тойрон $\\\\omega$ өнцөг хурдтай эргэлдэнэ. Цилиндрийн радиус $a$, нэгж уртад ногдох цэнэг $\\\\lambda$ бол цилиндрийн нэгж уртад ногдох соронзон орны энергийг ол ($\\\\mu = 1$)."
        }
      ],
      "answer": [
        {
          "type": "text",
          "value": "$W_{1}=\\mu_{0} \\lambda^{2} \\omega^{2} a^{2} / 8 \\pi$."
        }
      ]
    },
    {
      "type": "problem",
      "number": "3.340",
      "title": "",
      "statement": [
        {
          "type": "text",
          "value": "Вакуум дахь цахилгаан орны энергийн эзлэхүүн нягт нь $B = 1.0$ Тл индукцтэй соронзон орныхтой ижил байх үеийн цахилгаан орны хүчлэгийг ол."
        }
      ],
      "answer": [
        {
          "type": "text",
          "value": "$E=B / \\sqrt{\\varepsilon_{0} \\mu_{0}}=3 \\cdot 10^{8} \\mathrm{~В} / \\mathrm{м}$."
        }
      ]
    },
    {
      "type": "problem",
      "number": "3.341",
      "title": "",
      "statement": [
        {
          "type": "text",
          "value": "$a = 10$ см радиустай, жигд цэнэглэгдсэн нимгэн цагираг өөрийн тэнхлэгийг тойрон $\\\\omega = 100$ рад/с өнцөг хурдтай эргэлдэнэ. Цагирагны тэнхлэг дээр, түүний төв боос $l = a$ зайд орших цэг дээрх соронзон ба цахилгаан орны энергийн эзлэхүүн нягтуудын харьцааг ол."
        }
      ],
      "answer": [
        {
          "type": "text",
          "value": "$w_{m} / w_{e}=\\varepsilon_{0} \\mu_{0} \\omega^{2} a^{4} / l^{2}=1.1 \\cdot 10^{-15}$.\n3.343.\n(a) $L_{\\text {total }}=2 L$;\n(b) $L_{\\text {total }}=L / 2$."
        }
      ]
    },
    {
      "type": "problem",
      "number": "3.342",
      "title": "",
      "statement": [
        {
          "type": "text",
          "value": "Соронзон орны энергийн эзлэхүүн нягтын илэрхийллийг ашиглан нэгж эзэлхүүн пара- эсвэл диамагнитийн соронзлоход зарцуулагдах ажил $A = -JB/2$ болохыг харуул."
        }
      ],
      "answer": [
        {
          "type": "text",
          "value": "Хариу тооцоолох боломжгүй (ном дэх хариуны хүснэгтэд байхгүй)."
        }
      ]
    },
    {
      "type": "problem",
      "number": "3.343",
      "title": "",
      "statement": [
        {
          "type": "text",
          "value": "$L$ индукцлэлтэй хоёр ижил ороомгийг (а) цуваа, (б) зэрэгцээ холбов. Ороомгуудын харилцан индукцлэлийг тооцохгүйгээр системийн ерөнхий индукцлэлийг ол."
        }
      ],
      "answer": [
        {
          "type": "text",
          "value": "(a) $L_{\\text {total }}=2 L$; (b) $L_{\\text {total }}=L / 2$."
        }
      ]
    },
    {
      "type": "problem",
      "number": "3.344",
      "title": "",
      "statement": [
        {
          "type": "text",
          "value": "Ижил урттай, хөндлөн огтлолын талбайнууд нь бараг тэнцүү хоёр соленоид нэг нэгнийхээ дотор байрлана. Хэрэв тэдгээрийн индукцлэлүүд $L_1$ ба $L_2$ бол харилцан индукцлэлийг нь ол."
        }
      ],
      "answer": [
        {
          "type": "text",
          "value": "$L_{12}=\\sqrt{L_{1} L_{2}}$."
        }
      ]
    },
    {
      "type": "problem",
      "number": "3.345",
      "title": "",
      "statement": [
        {
          "type": "text",
          "value": "Вакуумд орших гүйдэлтэй хоёр хүрээний харилцан үйлчлэлийн соронзон энергийг $W_{12} = \\\\frac{1}{\\\\mu_0} \\\\int \\\\mathbf{B}_1 \\\\mathbf{B}_2 dV$ гэж илэрхийлж болохыг нотол. Үүнд $\\\\mathbf{B}_1$ ба $\\\\mathbf{B}_2$ нь нэгдүгээр ба хоёрдугаар хүрээний гүйдлүүдийн $dV$ эзлэхүүнд үүсгэх соронзон индукцүүд болно."
        }
      ],
      "answer": [
        {
          "type": "text",
          "value": "Хариу тооцоолох боломжгүй (ном дэх хариуны хүснэгтэд байхгүй)."
        }
      ]
    },
    {
      "type": "problem",
      "number": "3.346",
      "title": "",
      "statement": [
        {
          "type": "text",
          "value": "$I_1$ ба $I_2$ гүйдэлтэй, $a$ ба $b$ радиустай ($a \\\\ll b$) хоёр дугуй хүрээний харилцан үйлчлэлийн энергийг ол. Хүрээнүүдийн төвүүд давхцах бөгөөд тэдгээрийн хавтгайнууд хоорондоо $\\\\theta$ өнцөг үүсгэнэ."
        }
      ],
      "answer": [
        {
          "type": "text",
          "value": "$W_{12}=\\frac{\\mu_{0} \\pi a^{2}}{2 b} I_{1} I_{2} \\cos \\ta$."
        }
      ]
    },
    {
      "type": "problem",
      "number": "3.347",
      "title": "",
      "statement": [
        {
          "type": "text",
          "value": "Хоёр төвлөрсөн металл бөмбөлгийн хоорондох орон зай $\\\\rho$ хувийн эсэргүүцэлтэй, $\\\\varepsilon$ диэлектрик нэвтрүүлэх чадвартай нэгэн төрлийн муу дамжуулагч орчноор дүүргэгджээ. $t=0$ агшинд дотоод бөмбөлөгт тодорхой цэнэг өгөв. Дараах зүйлсийг ол:\n(а) нэгэн зэрэг, дурын цэг дэх шилжилтийн гүйдлийн нягт ба дамжуулах гүйдлийн нягтын векторуудын хоорондын хамаарал;\n(б) дотоод бөмбөлгийг хүрээлсэн, дурын битүү гадаргуугаар нэвтрэх шилжилтийн гүйдлийг тухайн агшин дахь бөмбөлгийн цэнэг $q$-ээр илэрхийлж ол."
        }
      ],
      "answer": [
        {
          "type": "text",
          "value": "(a) $\\mathbf{j}_{d}=-\\mathbf{j}$; (b) $I_{d}=q / \\varepsilon_{0} \\varepsilon \\rho$."
        }
      ]
    },
    {
      "type": "problem",
      "number": "3.348",
      "title": "",
      "statement": [
        {
          "type": "text",
          "value": "Хавтгай конденсаторын ялтсуудын хоорондох орон зай нэгэн төрлийн муу дамжуулагч орчноор дүүргэгджээ. Конденсаторыг цэнэглээд тэжээлээс салгав. Ирмэгийн эффектийг тооцохгүйгээр конденсаторын ялтсуудын хооронд соронзон орон байхгүйг харуул."
        }
      ],
      "answer": [
        {
          "type": "text",
          "value": "Дамжуулах гүйдлээс гадна шилжилтийн гүйдлийг тооцох шаардлагатай."
        }
      ]
    },
    {
      "type": "problem",
      "number": "3.349",
      "title": "",
      "statement": [
        {
          "type": "text",
          "value": "Ялтсуудын талбай нь $S = 100$ см$^2$ байх агаарын хавтгай конденсатор хувьсагч гүйдлийн хэлхээнд цуваа холбогджээ. Дамжуулах утсаар гүйх синусоид гүйдлийн далайц $I_m = 1.0$ мА, давтамж нь $\\\\omega = 1.6 \\\\cdot 10^7$ с$^{-1}$ бол конденсатор доторх цахилгаан орны хүчлэгийн далайцыг ол."
        }
      ],
      "answer": [
        {
          "type": "text",
          "value": "$E_{m}=I_{m} / \\varepsilon_{0} \\omega S=7 \\mathrm{~В} / \\mathrm{сm}$."
        }
      ]
    },
    {
      "type": "problem",
      "number": "3.350",
      "title": "",
      "statement": [
        {
          "type": "text",
          "value": "Хавтгай конденсаторын электродуудын хоорондох орон зай $\\\\sigma$ хувийн дамжуулалтай, $\\\\varepsilon$ диэлектрик нэвтрүүлэх чадвартай нэгэн төрлийн муу дамжуулагчаар дүүргэгджээ. Дугуй хэлбэртэй ялтсууд хоорондоо $d$ зайд оршино. Ирмэгийн эффектийг тооцохгүйгээр конденсаторт $V = V_m \\\\cos \\\\omega t$ хувьсах хүчдэл өгөхөд ялтсуудын хооронд, тэнхлэгээс $r$ зайд орших соронзон орны хүчлэгийг ол."
        }
      ],
      "answer": [
        {
          "type": "text",
          "value": "$H=H_{m} \\cos (\\omega t+\\alpha), $ энд $ H_{m}=\\frac{r V_{m}}{2 d} \\sqrt{\\sigma^{2}+\\left(\\varepsilon_{0} \\varepsilon \\omega\\right)^{2}}$ ба $\\alpha$ нь $\\tan \\alpha=\\varepsilon_{0} \\varepsilon \\omega / \\sigma$ томьёогоор тодорхойлогдоно."
        }
      ]
    },
    {
      "type": "problem",
      "number": "3.351",
      "title": "",
      "statement": [
        {
          "type": "text",
          "value": "Урт шулуун соленоид нэгж уртад $n$ ороодолтой болно. Түүгээр $I = I_m \\\\sin \\\\omega t$ хувьсах гүйдэл гүйж байна. Шилжилтийн гүйдлийн нягтыг соленоидын тэнхлэгээс алслах $r$ зайнаас хамааруулан ол. Соленоидын хөндлөн огтлолын радиус $R$ болно."
        }
      ],
      "answer": [
        {
          "type": "text",
          "value": "$j_{d}= \\begin{cases}1 / 2 \\ddot{B} r & \\text { үед } r<R,\n1 / 2 \\ddot{B} R^{2} / r & \\text { үед } r>R.\\end{cases}$\nЭнд $\\ddot{B}=\\mu_{0} n I_{m} \\omega^{2} \\sin \\omega t$.\n3.352.\n(a) $\\mathbf{j}_{d}=\\frac{2 q \\mathbf{v}}{4 \\pi r^{3}}$;\n(b) $\\mathbf{j}_{d}=-\\frac{q \\mathbf{v}}{4 \\pi r^{3}}$."
        }
      ]
    },
    {
      "type": "problem",
      "number": "3.352",
      "title": "",
      "statement": [
        {
          "type": "text",
          "value": "$q$ цэгэн цэнэг релятивист бус $\\\\mathbf{v} =$ const хурдтай хөдөлнө. Цэнэгээс $r$ зайд орших цэг дээрх шилжилтийн гүйдлийн нягт $\\\\mathbf{j}_d$-г дараах тохиолдолд ол:\n(а) цэг нь цэнэгийн хөдөлгөөний шулуун дээр байх;\n(б) цэг нь цэнэгийн хөдөлгөөний замд перпендикуляр, цэнэгийг дайран өнгөрөх шулуун дээр байх."
        }
      ],
      "answer": [
        {
          "type": "text",
          "value": "(a) \\(j_d = q v/(4\\pi r^3)\\) (диполийн тэнхлэгийн дагуух бүрэлдэхүүн); (b) \\(j_d = q v/(4\\pi r^3)\\). Энд \\(\\ddot{B}=\\mu_{0} n I_{m} \\omega^{2} \\sin \\omega t\\)."
        }
      ]
    },
    {
      "type": "problem",
      "number": "3.353",
      "title": "",
      "statement": [
        {
          "type": "text",
          "value": "$q$ цэнэгтэй, $a$ радиустай нимгэн утсан цагираг тогтмол $v$ хурдтайгаар $P$ цэгийг чиглэн шулуун замаар хөдөлнө. Цагирагны хавтгай хөдөлгөөний чиглэлд перпендикуляр хэвээр байна. $P$ цэг дээрх шилжилтийн гүйдлийн нягт хамгийн их байх үед цагираг $P$ цэгээс $x_m$ ямар зайд байх вэ? Энэ хамгийн их нягтыг ол."
        }
      ],
      "answer": [
        {
          "type": "text",
          "value": "$x_{m}=0, j_{d \\text { max }}=\\frac{q v}{4 \\pi a^{3}}$."
        }
      ]
    },
    {
      "type": "problem",
      "number": "3.354",
      "title": "",
      "statement": [
        {
          "type": "text",
          "value": "$q$ цэгэн цэнэг релятивист бус $\\\\mathbf{v} =$ const хурдтай хөдөлнө. 3.97-р зурагт үзүүлсэн тасархай тойргоор $\\\\mathbf{H}$ векторын циркуляцийн теоремыг ашиглан $A$ цэг дээрх соронзон орны хүчлэг $\\\\mathbf{H}$-ийг $r$ радиус-вектор ба цэнэгийн хурд $v$-ээр илэрхийлж ол."
        }
      ],
      "answer": [
        {
          "type": "text",
          "value": "$\\mathrm{H}=\\frac{q[\\mathrm{vr}]}{4 \\pi r^{3}}$."
        }
      ]
    },
    {
      "type": "problem",
      "number": "3.355",
      "title": "",
      "statement": [
        {
          "type": "text",
          "value": "Максвеллийн тэгшитгэлүүдийг ашиглан дараах зүйлсийг харуул:\n(а) хугацаанаас хамааран өөрчлөгдөх соронзон орон цахилгаан оронгүйгээр оршин тогтнох боломжгүй;\n(б) хугацаанаас хамааран өөрчлөгдөх соронзон орон байгаа үед нэгэн төрлийн цахилгаан орон байж болохгүй;\n(в) вакуум дотор нэгэн төрлийн цахилгаан (эсвэл соронзон) орон хугацаанаас хамааран өөрчлөгдөж болно (шугаман хуулиар)."
        }
      ],
      "answer": [
        {
          "type": "text",
          "value": "(а) Хэрэв $\\\\mathbf{B}(t)$ бол $\\\\boldsymbol{\\\\nabla} \\\\times \\\\mathbf{E} = -\\\\partial \\\\mathbf{B} / \\\\partial t \\\\neq 0$ болно. Цахилгаан орны хүчлэгийн ротор тэгээс ялгаатай байх ($\\\\boldsymbol{\\\\nabla} \\\\times \\\\mathbf{E} \\\\neq 0$) нь зөвхөн цахилгаан орон байгаа тохиолдолд л боломжтой.\n(б) Хэрэв $\\\\mathbf{B}(t)$ бол $\\\\boldsymbol{\\\\nabla} \\\\times \\\\mathbf{E} = -\\\\partial \\\\mathbf{B} / \\\\partial t \\\\neq 0$ болно. Гэтэл нэгэн төрлийн орны хувьд $\\\\boldsymbol{\\\\nabla} \\\\times \\\\mathbf{E} = 0$ байдаг.\n(в) $\\\\mathbf{E} = \\\\mathbf{a}f(t)$ гэж үзье. Үүнд $\\\\mathbf{a}$ нь координатаас хамаарахгүй вектор, $f(t)$ нь хугацааны дурын функц юм. Тэгвэл $-\\\\partial \\\\mathbf{B} / \\\\partial t = \\\\boldsymbol{\\\\nabla} \\\\times \\\\mathbf{E} = 0$ буюу соронзон орон хугацаанаас хамаарахгүй байх ёстой. Ерөнхий тохиолдолд энэ нь $\\\\boldsymbol{\\\\nabla} \\\\times \\\\mathbf{H} = \\\\partial \\\\mathbf{D} / \\\\partial t$ тэгшитгэлтэй зөрчилдөнө (зүүн гар тал нь хугацаанаас хамаарахгүй байхад баруун гар тал нь хамаарна). Гэхдээ $f(t)$ нь хугацааны шугаман функц байх тохиолдолд энэ зөрчил арилж, нэгэн төрлийн цахилгаан орон хугацаанаас хамаарч болох боломжтой болно."
        }
      ]
    },
    {
      "type": "problem",
      "number": "3.356",
      "title": "",
      "statement": [
        {
          "type": "text",
          "value": "Цэнэгийн хадгалагдах хууль буюу $\\\\boldsymbol{\\\\nabla} \\\\cdot \\\\mathbf{j} = -\\\\partial \\\\rho / \\\\partial t$ нь Максвеллийн тэгшитгэлүүдээс мөрдөн гардаг болохыг харуул."
        }
      ],
      "answer": [
        {
          "type": "text",
          "value": "$\\boldsymbol{\\\\nabla} \\\\times \\\\mathbf{H}=\\\\mathbf{j}+\\\\partial \\\\mathbf{D} / \\\\partial t$ тэгшитгэлийн хоёр талын дивергенцийг олъё. Роторын дивергенц үргэлж тэгтэй тэнцүү байдаг тул $0=\\\\boldsymbol{\\\\nabla} \\\\cdot \\\\mathbf{j}+\\\\frac{\\\\partial}{\\\\partial t}(\\\\boldsymbol{\\\\nabla} \\\\cdot \\\\mathbf{D})$ болно. Одоо $\\\\boldsymbol{\\\\nabla} \\\\cdot \\\\mathbf{D}=\\\\rho$ гэдгийг тооцоход л хангалттай."
        }
      ]
    },
    {
      "type": "problem",
      "number": "3.357",
      "title": "",
      "statement": [
        {
          "type": "text",
          "value": "Максвеллийн $\\\\boldsymbol{\\\\nabla} \\\\times \\\\mathbf{E} = -\\\\partial \\\\mathbf{B} / \\\\partial t$ ба $\\\\boldsymbol{\\\\nabla} \\\\cdot \\\\mathbf{B} = 0$ тэгшитгэлүүд хоорондоо нийцтэй (зөрчилгүй) болохыг харуул."
        }
      ],
      "answer": [
        {
          "type": "text",
          "value": "Эхний тэгшитгэлийн хоёр талын дивергенцийг авч үзье. Роторын дивергенц үргэлж тэгтэй тэнцүү байдаг тул $\\\\boldsymbol{\\\\nabla} \\\\cdot(\\\\partial \\\\mathbf{B} / \\\\partial t)=0$ эсвэл $\\\\frac{\\\\partial}{\\\\partial t}(\\\\boldsymbol{\\\\nabla} \\\\cdot \\\\mathbf{B})=0$ болно. Иймд $\\\\boldsymbol{\\\\nabla} \\\\cdot \\\\mathbf{B}=$ тогтмол бөгөөд энэ нь хоёр дахь тэгшитгэлтэй зөрчилдөхгүй."
        }
      ]
    },
    {
      "type": "problem",
      "number": "3.358",
      "title": "",
      "statement": [
        {
          "type": "text",
          "value": "Инерциал тооллын системд орших тодорхой мужид $B$ индукцтэй соронзон орон $\\\\boldsymbol{\\\\omega}$ өнцөг хурдтайгаар эргэлдэж байна. Энэ муж дахь $\\\\boldsymbol{\\\\nabla} \\\\times \\\\mathbf{E}$ роторыг $\\\\boldsymbol{\\\\omega}$ ба $\\\\mathbf{B}$ вектороор илэрхийлж ол."
        }
      ],
      "answer": [
        {
          "type": "text",
          "value": "$\\boldsymbol{\\\\nabla} \\\\times \\\\mathbf{E}=-[\\\\boldsymbol{\\\\omega}} \\\\mathbf{B}]$."
        }
      ]
    },
    {
      "type": "problem",
      "number": "3.359",
      "title": "",
      "statement": [
        {
          "type": "text",
          "value": "$K$ инерциал системд $B$ индукцтэй нэгэн төрлийн соронзон орон байна. $K$ системтэй харьцангуй $v$ ($v \\\\perp \\\\mathbf{B}$) хурдтай хөдөлж буй $K'$ систем дэх цахилгаан орны хүчлэгийг ол. Бодолтод $K'$ системд тайван байгаа цэгэн цэнэгт үйлчлэх хүчийг хоёр системд авч үзнэ."
        }
      ],
      "answer": [
        {
          "type": "text",
          "value": "$\\mathbf{E}^{\\prime}=[\\mathbf{vB}]$."
        }
      ]
    },
    {
      "type": "problem",
      "number": "3.360",
      "title": "",
      "statement": [
        {
          "type": "text",
          "value": "Цахилгаан дамжуулагч (соронзон бус) материалаар хийсэн том хавтан $B = 50$ мТл индукцтэй нэгэн төрлийн соронзон оронд $v = 90$ см/с тогтмол хурдтайгаар 3.98-р зурагт үзүүлсэн шиг хөдөлнө. Хөдөлгөөний явцад хавтан дээр үүсэх индукцийн цэнэгийн гадаргуугийн нягтыг ол."
        }
      ],
      "answer": [
        {
          "type": "text",
          "value": "$\\sigma=\\varepsilon_{0} v B=0.40 \\mathrm{pC} / \\mathrm{м}^{2}$.\n3.361 $\\rho=-2 \\varepsilon \\omega \\mathrm{~B}=-0.08 \\mathrm{nC} / \\mathrm{м}^{3}, \\sigma=\\varepsilon_{0} a \\omega \\mathrm{~B}=2 \\mathrm{pC} / \\mathrm{м}^{2}$."
        }
      ]
    },
    {
      "type": "problem",
      "number": "3.361",
      "title": "",
      "statement": [
        {
          "type": "text",
          "value": "$a = 5.0$ см радиустай урт цул хөнгөн цагаан цилиндр $B = 10$ мТл индукцтэй нэгэн төрлийн соронзон оронд өөрийн тэнхлэгийг тойрон эргэлдэнэ. Эргэлтийн өнцөг хурд $\\\\omega = 45$ рад/с бөгөөд $\\\\boldsymbol{\\\\omega} \\\\uparrow\\\\uparrow \\\\mathbf{B}$ болкоор. Үүсэх цэнэгүүдийн соронзон орныг тооцохгүйгээр индукцийн цэнэгүүдийн эзлэхүүн ба гадаргуугийн нягтыг ол."
        }
      ],
      "answer": [
        {
          "type": "text",
          "value": "$\\rho = -2\\\\varepsilon_0 \\\\omega B = -0.08$ нКл/м$^3$; $\\\\sigma = \\\\varepsilon_0 \\\\omega B a = 2$ пКл/м$^2$."
        }
      ]
    },
    {
      "type": "problem",
      "number": "3.362",
      "title": "",
      "statement": [
        {
          "type": "text",
          "value": "Релятивист бус $q$ цэгэн цэнэг $v$ тогтмол хурдтай хөдөлнө. Орны хувиргалтын томьёог ашиглан цэнэгээс $r$ зайд орших цэг дээрх соронзон индукц $B$-г ол."
        }
      ],
      "answer": [
        {
          "type": "text",
          "value": "$\\mathbf{B}=\\frac{\\mu_{0}}{4 \\pi} \\frac{q[\\mathbf{v r}]}{r^{3}}$."
        }
      ]
    },
    {
      "type": "problem",
      "number": "3.363",
      "title": "",
      "statement": [
        {
          "type": "text",
          "value": "Орны хувиргалтын (3.6h) томьёог ашиглан хэрэв $K$ инерциал системд зөвхөн цахилгаан (эсвэл зөвхөн соронзон) орон байвал дурын өөр $K'$ системд $\\\\mathbf{E}' \\\\perp \\\\mathbf{B}'$ байх цахилгаан ба соронзон орнууд нэгэн зэрэг оршино гэдгийг харуул."
        }
      ],
      "answer": [
        {
          "type": "text",
          "value": "Хариу тооцоолох боломжгүй (ном дэх хариуны хүснэгтэд байхгүй)."
        }
      ]
    },
    {
      "type": "problem",
      "number": "3.364",
      "title": "",
      "statement": [
        {
          "type": "text",
          "value": "$K$ инерциал системд зөвхөн $\\\\mathbf{B} = b(y\\\\mathbf{i} - x\\\\mathbf{j}) / (x^2 + y^2)$ ($b$ - тогтмол) индукцтэй соронзон орон байв. $K$ системтэй харьцангуй $\\\\mathbf{v} = v\\\\mathbf{k}$ ($z$ тэнхлэгийн дагуу) хурдтай хөдөлж буй $K'$ систем дэх цахилгаан орны хүчлэг $\\\\mathbf{E}'$-ийг ол. Энэ орон ямар хэлбэртэй байх вэ?"
        }
      ],
      "answer": [
        {
          "type": "text",
          "value": "$\\mathbf{E}^{\\prime}=b \\mathbf{r} / r^{2}$, энд $r$ нь $z^{\\prime}$ тэнхлэгээс алслах зай."
        }
      ]
    },
    {
      "type": "problem",
      "number": "3.365",
      "title": "",
      "statement": [
        {
          "type": "text",
          "value": "$K$ инерциал системд зөвхөн $\\\\mathbf{E} = a(x\\\\mathbf{i} + y\\\\mathbf{j}) / (x^2 + y^2)$ ($a$ - тогтмол) хүчлэгтэй цахилгаан орон байв. $K$ системтэй харьцангуй $\\\\mathbf{v} = v\\\\mathbf{k}$ хурдтай хөдөлж буй $K'$ систем дэх соронзон индукц $\\\\mathbf{B}'$-ийг ол. Энэ орон ямар хэлбэртэй байх вэ?"
        }
      ],
      "answer": [
        {
          "type": "text",
          "value": "$\\mathbf{B}^{\\prime}=\\frac{a[\\mathrm{rv}]}{c^{2} r^{2}}$, энд $r$ нь $z^{\\prime}$ тэнхлэгээс алслах зай."
        }
      ]
    },
    {
      "type": "problem",
      "number": "3.366",
      "title": "",
      "statement": [
        {
          "type": "text",
          "value": "Хувиргах томьёо (3.6h) нь $v_{0} \\\\ll c$ дээрх (3.6i) томъёоноос дагалдаж байгааг харуул."
        }
      ],
      "answer": [
        {
          "type": "text",
          "value": "Хариу тооцоолох боломжгүй (ном дэх хариуны хүснэгтэд байхгүй)."
        }
      ]
    },
    {
      "type": "problem",
      "number": "3.367",
      "title": "",
      "statement": [
        {
          "type": "text",
          "value": "$K$ инерциал системд $E = 8$ кВ/м хүчлэгтэй нэгэн төрлийн цахилгаан орон байв. $K$ системтэй харьцангуй $v = 0.60c$ хурдтай, $\\\\mathbf{E}$ вектортой $\\\\alpha = 45^\\\\circ$ өнцөг үүсгэн хөдөлж буй $K'$ систем дэх (а) цахилгаан орны хүчлэг $\\\\mathbf{E}'$, (б) соронзон индукц $\\\\mathbf{B}'$-ийн хэмжээ ба чиглэлийг ол."
        }
      ],
      "answer": [
        {
          "type": "text",
          "value": "(a) $E^{\\prime}=E \\sqrt{\\frac{1-\\beta^{2} \\cos ^{2} \\alpha}{1-\\beta^{2}}}=9 \\mathrm{kV} / \\mathrm{м}; \\tan \\alpha^{\\prime}=\\frac{\\tan \\alpha}{\\sqrt{1-\\beta^{2}}}$, үүнээс $\\alpha \\approx 51^{\\circ}$; (b) $B^{\\prime}=\\frac{\\beta E \\sin \\alpha}{c \\sqrt{1-\\beta^{2}}}=14 \\mu \\mathrm{~T}$."
        }
      ]
    },
    {
      "type": "problem",
      "number": "3.368",
      "title": "",
      "statement": [
        {
          "type": "text",
          "value": "Өмнөх бодлогыг $E = 8$ кВ/м цахилгаан орны оронд $B = 0.8$ Тл соронзон орон байсан гэж үзээд бод."
        }
      ],
      "answer": [
        {
          "type": "text",
          "value": "(a) $E^{\\prime}=\\frac{\\beta B \\sin \\alpha}{c \\sqrt{1-\\beta^{2}}}=1.4 \\mathrm{nV} / \\mathrm{м}$;\n(b) $B^{\\prime}=B \\sqrt{\\frac{1-\\beta^{2} \\cos ^{2} \\alpha}{1-\\beta^{2}}}=0.9 \\mathrm{~T}, \\alpha^{\\prime} \\approx 51^{\\circ}$."
        }
      ]
    },
    {
      "type": "problem",
      "number": "3.369",
      "title": "",
      "statement": [
        {
          "type": "text",
          "value": "Цахилгаан соронзон орны хоёр инвариант байдаг. Орны хувиргалтын (3.6i) томьёог ашиглан (а) $\\\\mathbf{E} \\\\cdot \\\\mathbf{B}$ ба (б) $E^2 - c^2 B^2$ хэмжигдэхүүнүүд инвариант болохыг харуул."
        }
      ],
      "answer": [
        {
          "type": "text",
          "value": "Хариу тооцоолох боломжгүй (ном дэх хариуны хүснэгтэд байхгүй)."
        }
      ]
    },
    {
      "type": "problem",
      "number": "3.370",
      "title": "",
      "statement": [
        {
          "type": "text",
          "value": "$K$ инерциал системд харилцан перпендикуляр хоёр орон байна: $E = 40$ кВ/м хүчлэгтэй цахилгаан орон ба $B = 0.20$ мТл индукцтэй соронзон орон. Зөвхөн цахилгаан (эсвэл зөвхөн соронзон) орон ажиглагдах тэрхүү $K'$ инерциал систем дэх цахилгаан орны хүчлэг $E'$ (эсвэл соронзон индукц $B'$)-ийг ол. Заавар: Өмнөх бодлогын инвариантуудыг ашигла."
        }
      ],
      "answer": [
        {
          "type": "text",
          "value": "$B^{\\prime}=B \\sqrt{1-(E / c B)^{2}} \\approx 0.15 \\mathrm{mT}$."
        }
      ]
    },
    {
      "type": "problem",
      "number": "3.371",
      "title": "",
      "statement": [
        {
          "type": "text",
          "value": "$q$ цэгэн цэнэг $v = \\\\beta c$ хурдтайгаар шулуун замаар жигд хөдөлнө. Цэнэгээс $r$ зайд, хөдөлгөөний чиглэлтэй $\\\\theta$ өнцөг үүсгэх чиглэлд орших цэг дээрх цахилгаан орны хүчлэг $E$-г ол."
        }
      ],
      "answer": [
        {
          "type": "text",
          "value": "Лавлах $K$ системд $q$ цэнэг $x$ тэнхлэгийн эерэг чиглэлд хөдөлж байна гэж үзье. Цэнэг тайван орших $K'$ системд шилжье ($x$ ба $x'$ тэнхлэгүүд давхцаж, $y, y'$ тэнхлэгүүд параллель). $K'$ системд цэнэгийн үүсгэх орон хамгийн энгийн хэлбэртэй байна: $\\\\mathbf{E}' = \\\\frac{1}{4\\\\pi\\\\varepsilon_0} \\\\frac{q}{r'^3} \\\\mathbf{r}'$. $x, y$ хавтгай дахь проекцууд нь:\n$$\nE_x' = \\\\frac{1}{4\\\\pi\\\\varepsilon_0} \\\\frac{q}{r'^3} x', \\\\quad E_y' = \\\\frac{1}{4\\\\pi\\\\varepsilon_0} \\\\frac{q}{r'^3} y'.\n$$\nОдоо анхны $K$ системдээ буцаж шилжье. $q$ цэнэг $K$ системийн координат эх дээр байх агшинд $\\\\mathbf{r}$ векторын $x, y$ проекцууд нь $K'$ систем дэх $\\\\mathbf{r}'$ векторын $x', y'$ проекцуудтай дараах хамааралтай байна:\n$$\nx = r \\\\cos \\\\theta = x' \\\\sqrt{1-(v/c)^2}, \\\\quad y = r \\\\sin \\\\theta = y'.\n$$\nТүүнчлэн (3.6i) томьёоны урвуу хувиргалтаар:\n$$\nE_x = E_x', \\\\quad E_y = E_y' / \\\\sqrt{1-(v/c)^2}.\n$$\nЭдгээр тэгшитгэлүүдийг нэгтгэн бодвол:\n$$\n\\\\mathbf{E} = E_x \\\\mathbf{i} + E_y \\\\mathbf{j} = \\\\frac{1}{4\\\\pi\\\\varepsilon_0} \\\\frac{q \\\\mathbf{r}}{r^3} \\\\frac{1-\\\\beta^2}{(1-\\\\beta^2 \\\\sin^2 \\\\theta)^{3/2}}.\n$$\nЭнэ тохиолдолд ($v=$ const) $\\\\mathbf{E}$ вектор нь $\\\\mathbf{r}$ радиус-вектортой коллинеар (нэг шулуун дээр) байна."
        }
      ]
    }
  ]
}